{
  "info": {
    "_postman_id": "b96b331b-f7e7-4b67-bfe2-980ce7322e85",
    "name": "Demo REST API",
    "schema": "https://schema.getpostman.com/json/collection/v2.1.0/collection.json"
  },
  "item": [
    {
      "name": "Get Student by ID",
      "request": {
        "method": "GET",
        "header": [],
        "url": {
          "raw": "http://localhost:8080/api/students/1",
          "protocol": "http",
          "host": [
            "localhost"
          ],
          "port": "8080",
          "path": [
            "api",
            "students",
            "1"
          ]
        }
      },
      "response": []
    },
    {
      "name": "Get All Students",
      "request": {
        "method": "GET",
        "header": [],
        "url": {
          "raw": "http://localhost:8080/api/students",
          "protocol": "http",
          "host": [
            "localhost"
          ],
          "port": "8080",
          "path": [
            "api",
            "students"
          ]
        }
      },
      "response": []
    },
    {
      "name": "Add Student",
      "request": {
        "method": "POST",
        "header": [
          {
            "key": "Content-Type",
            "value": "application/json",
            "type": "text"
          }
        ],
        "body": {
          "mode": "raw",
          "raw": "{\"id\":3,\"name\":\"Jane Doe\",\"age\":28}"
        },
        "url": {
          "raw": "http://localhost:8080/api/students",
          "protocol": "http",
          "host": [
            "localhost"
          ],
          "port": "8080",
          "path": [
            "api",
            "students"
          ]
        }
      },
      "response": []
    },
    {
      "name": "Update Student",
      "request": {
        "method": "PUT",
        "header": [
          {
            "key": "Content-Type",
            "value": "application/json",
            "type": "text"
          }
        ],
        "body": {
          "mode": "raw",
          "raw": "{\"id\":1,\"name\":\"Updated Name\",\"age\":30}"
        },
        "url": {
          "raw": "http://localhost:8080/api/students/1",
          "protocol": "http",
          "host": [
            "localhost"
          ],
          "port": "8080",
          "path": [
            "api",
            "students",
            "1"
          ]
        }
      },
      "response": []
    },
    {
      "name": "Delete Student",
      "request": {
        "method": "DELETE",
        "header": [],
        "url": {
          "raw": "http://localhost:8080/api/students/1",
          "protocol": "http",
          "host": [
            "localhost"
          ],
          "port": "8080",
          "path": [
            "api",
            "students",
            "1"
          ]
        }
      },
      "response": []
    }
  ]
}
